Workbook

Sheet Assumptions
A1: UBHI — FINANCIAL MODEL · ASSUMPTIONS
A2: Edit the blue cells. The other two tabs recalculate automatically.
A4: SNAIL MAIL CLUB (art-by-post subscription)
A5: Blended price per subscriber / month | B5: 16 | C5: £18 monthly · £16.33 3-mo · £15.83 6-mo · £12.42 12-mo
A6: Subscribers at launch | B6: 0 | C6: Start from zero
A7: New subscribers gained / month (Year 1) | B7: 10 | C7: Organic, no ad budget
A8: Monthly churn (cancellations) | B8: 0.08 | C8: Lifestyle-box benchmark 8–14%/mo (verified)
A9: Cost per parcel (materials + UK postage) | B9: 6 | C9: Paper, art, object, stamp
A11: SOUL SHOP (handmade goods)
A12: Orders / month (full Year-1 run-rate) | B12: 15 | C12: Own-site, organic traffic
A13: Average order value (AOV) | B13: 35 | C13: Items £8–68, free post over £50
A14: Materials cost (% of shop revenue) | B14: 0.35 | C14: ~65% gross margin before labour
A16: WORKSHOPS (your corrected model)
A17: Ticket price per person | B17: 35 | C17: London social-class sweet spot £10–43 (verified)
A18: Seats per workshop (capacity) | B18: 15 | C18: Your figure
A19: Fill rate (target, seats sold) | B19: 0.75 | C19: Realistic for a building brand; 100% = full house
A20: Workshops per month | B20: 8 | C20: 2 per week — your figure
A21: Venue hire per workshop | B21: 180 | C21: Per-session; a fixed studio slashes this
A22: Materials per attendee | B22: 7 | C22: Inks, paper, clay, kits
A24: OVERHEADS & FEES
A25: Website / hosting / month | B25: 20 | C25: Domain, host, backend
A26: Marketing / misc / month | B26: 50 | C26: Props, samples, small ads
A27: Payment fees (% of revenue) | B27: 0.02 | C27: Stripe ~1.5% + 20p
A29: YEAR-1 BUILD & GROWTH
A30: Year-1 ramp — Month 1 as % of run-rate | B30: 0.4 | C30: Starts slow, reaches 100% by M12
A31: Snail Mail — Year 2 (× Year 1) | B31: 2.5 | C31: Recurring base compounds
A32: Snail Mail — Year 3 (× Year 1) | B32: 3.5 | C32: Approaching solo capacity ceiling
A33: Soul Shop — Year 2 (× Year 1) | B33: 1.8 | C33: Traffic & repeat build
A34: Soul Shop — Year 3 (× Year 1) | B34: 2.5
A35: Workshops — Year 2 (× Year 1) | B35: 1.3 | C35: Add private/corporate bookings
A36: Workshops — Year 3 (× Year 1) | B36: 1.6 | C36: Fixed studio + reputation
A37: Overhead growth / year (×) | B37: 1.4 | C37: You reinvest as you grow

Sheet Year 1 Cash Flow
A1: YEAR 1 — MONTHLY CASH FLOW (£)
B3: M1 | C3: M2 | D3: M3 | E3: M4 | F3: M5 | G3: M6 | H3: M7 | I3: M8 | J3: M9 | K3: M10 | L3: M11 | M3: M12 | N3: YEAR 1
A4: Ramp factor (Y1 build) | B4: ='Assumptions'!$B$30+(1-'Assumptions'!$B$30)*0/11 -> 0.4 | C4: ='Assumptions'!$B$30+(1-'Assumptions'!$B$30)*1/11 -> 0.45454545 | D4: ='Assumptions'!$B$30+(1-'Assumptions'!$B$30)*2/11 -> 0.50909091 | E4: ='Assumptions'!$B$30+(1-'Assumptions'!$B$30)*3/11 -> 0.56363636 | F4: ='Assumptions'!$B$30+(1-'Assumptions'!$B$30)*4/11 -> 0.61818182 | G4: ='Assumptions'!$B$30+(1-'Assumptions'!$B$30)*5/11 -> 0.67272727 | H4: ='Assumptions'!$B$30+(1-'Assumptions'!$B$30)*6/11 -> 0.72727273 | I4: ='Assumptions'!$B$30+(1-'Assumptions'!$B$30)*7/11 -> 0.78181818 | J4: ='Assumptions'!$B$30+(1-'Assumptions'!$B$30)*8/11 -> 0.83636364 | K4: ='Assumptions'!$B$30+(1-'Assumptions'!$B$30)*9/11 -> 0.89090909 | L4: ='Assumptions'!$B$30+(1-'Assumptions'!$B$30)*10/11 -> 0.94545455 | M4: ='Assumptions'!$B$30+(1-'Assumptions'!$B$30)*11/11 -> 1
A5: REVENUE
A6: Snail Mail — active subscribers | B6: =ROUND('Assumptions'!$B$6*(1-'Assumptions'!$B$8)+'Assumptions'!$B$7,0) -> 10 | C6: =ROUND(B6*(1-'Assumptions'!$B$8)+'Assumptions'!$B$7,0) -> 19 | D6: =ROUND(C6*(1-'Assumptions'!$B$8)+'Assumptions'!$B$7,0) -> 27 | E6: =ROUND(D6*(1-'Assumptions'!$B$8)+'Assumptions'!$B$7,0) -> 35 | F6: =ROUND(E6*(1-'Assumptions'!$B$8)+'Assumptions'!$B$7,0) -> 42 | G6: =ROUND(F6*(1-'Assumptions'!$B$8)+'Assumptions'!$B$7,0) -> 49 | H6: =ROUND(G6*(1-'Assumptions'!$B$8)+'Assumptions'!$B$7,0) -> 55 | I6: =ROUND(H6*(1-'Assumptions'!$B$8)+'Assumptions'!$B$7,0) -> 61 | J6: =ROUND(I6*(1-'Assumptions'!$B$8)+'Assumptions'!$B$7,0) -> 66 | ... M6: =ROUND(L6*(1-'Assumptions'!$B$8)+'Assumptions'!$B$7,0) -> 79 | N6: =ROUND(AVERAGE(B6:M6),0) -> 49
A7: Snail Mail — revenue | B7: =B6*'Assumptions'!$B$5 -> 160 | C7: =C6*'Assumptions'!$B$5 -> 304 | D7: =D6*'Assumptions'!$B$5 -> 432 | E7: =E6*'Assumptions'!$B$5 -> 560 | F7: =F6*'Assumptions'!$B$5 -> 672 | G7: =G6*'Assumptions'!$B$5 -> 784 | H7: =H6*'Assumptions'!$B$5 -> 880 | I7: =I6*'Assumptions'!$B$5 -> 976 | ... M7: =M6*'Assumptions'!$B$5 -> 1264 | N7: =SUM(B7:M7) -> 9424
A8: Soul Shop — orders | B8: =ROUND('Assumptions'!$B$12*B4,0) -> 6 | C8: =ROUND('Assumptions'!$B$12*C4,0) -> 7 | D8: =ROUND('Assumptions'!$B$12*D4,0) -> 8 | E8: =ROUND('Assumptions'!$B$12*E4,0) -> 8 | F8: =ROUND('Assumptions'!$B$12*F4,0) -> 9 | G8: =ROUND('Assumptions'!$B$12*G4,0) -> 10 | H8: =ROUND('Assumptions'!$B$12*H4,0) -> 11 | I8: =ROUND('Assumptions'!$B$12*I4,0) -> 12 | ... M8: =ROUND('Assumptions'!$B$12*M4,0) -> 15 | N8: =SUM(B8:M8) -> 126
A9: Soul Shop — revenue | B9: =B8*'Assumptions'!$B$13 -> 210 | C9: =C8*'Assumptions'!$B$13 -> 245 | D9: =D8*'Assumptions'!$B$13 -> 280 | E9: =E8*'Assumptions'!$B$13 -> 280 | F9: =F8*'Assumptions'!$B$13 -> 315 | G9: =G8*'Assumptions'!$B$13 -> 350 | H9: =H8*'Assumptions'!$B$13 -> 385 | I9: =I8*'Assumptions'!$B$13 -> 420 | ... M9: =M8*'Assumptions'!$B$13 -> 525 | N9: =SUM(B9:M9) -> 4410
A10: Workshops — seats sold | B10: =ROUND('Assumptions'!$B$20*'Assumptions'!$B$18*'Assumptions'!$B$19*B4,0) -> 36 | C10: =ROUND('Assumptions'!$B$20*'Assumptions'!$B$18*'Assumptions'!$B$19*C4,0) -> 41 | D10: =ROUND('Assumptions'!$B$20*'Assumptions'!$B$18*'Assumptions'!$B$19*D4,0) -> 46 | E10: =ROUND('Assumptions'!$B$20*'Assumptions'!$B$18*'Assumptions'!$B$19*E4,0) -> 51 | F10: =ROUND('Assumptions'!$B$20*'Assumptions'!$B$18*'Assumptions'!$B$19*F4,0) -> 56 | G10: =ROUND('Assumptions'!$B$20*'Assumptions'!$B$18*'Assumptions'!$B$19*G4,0) -> 61 | H10: =ROUND('Assumptions'!$B$20*'Assumptions'!$B$18*'Assumptions'!$B$19*H4,0) -> 65 | I10: =ROUND('Assumptions'!$B$20*'Assumptions'!$B$18*'Assumptions'!$B$19*I4,0) -> 70 | ... M10: =ROUND('Assumptions'!$B$20*'Assumptions'!$B$18*'Assumptions'!$B$19*M4,0) -> 90 | N10: =SUM(B10:M10) -> 756
A11: Workshops — revenue | B11: =B10*'Assumptions'!$B$17 -> 1260 | C11: =C10*'Assumptions'!$B$17 -> 1435 | D11: =D10*'Assumptions'!$B$17 -> 1610 | E11: =E10*'Assumptions'!$B$17 -> 1785 | F11: =F10*'Assumptions'!$B$17 -> 1960 | G11: =G10*'Assumptions'!$B$17 -> 2135 | H11: =H10*'Assumptions'!$B$17 -> 2275 | I11: =I10*'Assumptions'!$B$17 -> 2450 | ... M11: =M10*'Assumptions'!$B$17 -> 3150 | N11: =SUM(B11:M11) -> 26460
A12: TOTAL REVENUE | B12: =B7+B9+B11 -> 1630 | C12: =C7+C9+C11 -> 1984 | D12: =D7+D9+D11 -> 2322 | E12: =E7+E9+E11 -> 2625 | F12: =F7+F9+F11 -> 2947 | G12: =G7+G9+G11 -> 3269 | H12: =H7+H9+H11 -> 3540 | I12: =I7+I9+I11 -> 3846 | ... M12: =M7+M9+M11 -> 4939 | N12: =SUM(B12:M12) -> 40294
A14: EXPENSES
A15: Snail Mail — materials & postage | B15: =B6*'Assumptions'!$B$9 -> 60 | C15: =C6*'Assumptions'!$B$9 -> 114 | D15: =D6*'Assumptions'!$B$9 -> 162 | E15: =E6*'Assumptions'!$B$9 -> 210 | F15: =F6*'Assumptions'!$B$9 -> 252 | G15: =G6*'Assumptions'!$B$9 -> 294 | H15: =H6*'Assumptions'!$B$9 -> 330 | I15: =I6*'Assumptions'!$B$9 -> 366 | ... M15: =M6*'Assumptions'!$B$9 -> 474 | N15: =SUM(B15:M15) -> 3534
A16: Soul Shop — materials | B16: =B9*'Assumptions'!$B$14 -> 73.5 | C16: =C9*'Assumptions'!$B$14 -> 85.75 | D16: =D9*'Assumptions'!$B$14 -> 98 | E16: =E9*'Assumptions'!$B$14 -> 98 | F16: =F9*'Assumptions'!$B$14 -> 110.25 | G16: =G9*'Assumptions'!$B$14 -> 122.5 | H16: =H9*'Assumptions'!$B$14 -> 134.75 | I16: =I9*'Assumptions'!$B$14 -> 147 | ... M16: =M9*'Assumptions'!$B$14 -> 183.75 | N16: =SUM(B16:M16) -> 1543.5
A17: Workshops — venue hire | B17: ='Assumptions'!$B$20*'Assumptions'!$B$21 -> 1440 | C17: ='Assumptions'!$B$20*'Assumptions'!$B$21 -> 1440 | D17: ='Assumptions'!$B$20*'Assumptions'!$B$21 -> 1440 | E17: ='Assumptions'!$B$20*'Assumptions'!$B$21 -> 1440 | F17: ='Assumptions'!$B$20*'Assumptions'!$B$21 -> 1440 | G17: ='Assumptions'!$B$20*'Assumptions'!$B$21 -> 1440 | H17: ='Assumptions'!$B$20*'Assumptions'!$B$21 -> 1440 | I17: ='Assumptions'!$B$20*'Assumptions'!$B$21 -> 1440 | ... M17: ='Assumptions'!$B$20*'Assumptions'!$B$21 -> 1440 | N17: =SUM(B17:M17) -> 17280
A18: Workshops — materials | B18: =B10*'Assumptions'!$B$22 -> 252 | C18: =C10*'Assumptions'!$B$22 -> 287 | D18: =D10*'Assumptions'!$B$22 -> 322 | E18: =E10*'Assumptions'!$B$22 -> 357 | F18: =F10*'Assumptions'!$B$22 -> 392 | G18: =G10*'Assumptions'!$B$22 -> 427 | H18: =H10*'Assumptions'!$B$22 -> 455 | I18: =I10*'Assumptions'!$B$22 -> 490 | ... M18: =M10*'Assumptions'!$B$22 -> 630 | N18: =SUM(B18:M18) -> 5292
A19: Payment processing fees | B19: =B12*'Assumptions'!$B$27 -> 32.6 | C19: =C12*'Assumptions'!$B$27 -> 39.68 | D19: =D12*'Assumptions'!$B$27 -> 46.44 | E19: =E12*'Assumptions'!$B$27 -> 52.5 | F19: =F12*'Assumptions'!$B$27 -> 58.94 | G19: =G12*'Assumptions'!$B$27 -> 65.38 | H19: =H12*'Assumptions'!$B$27 -> 70.8 | I19: =I12*'Assumptions'!$B$27 -> 76.92 | ... M19: =M12*'Assumptions'!$B$27 -> 98.78 | N19: =SUM(B19:M19) -> 805.88
A20: Overheads (web, marketing) | B20: ='Assumptions'!$B$25+'Assumptions'!$B$26 -> 70 | C20: ='Assumptions'!$B$25+'Assumptions'!$B$26 -> 70 | D20: ='Assumptions'!$B$25+'Assumptions'!$B$26 -> 70 | E20: ='Assumptions'!$B$25+'Assumptions'!$B$26 -> 70 | F20: ='Assumptions'!$B$25+'Assumptions'!$B$26 -> 70 | G20: ='Assumptions'!$B$25+'Assumptions'!$B$26 -> 70 | H20: ='Assumptions'!$B$25+'Assumptions'!$B$26 -> 70 | I20: ='Assumptions'!$B$25+'Assumptions'!$B$26 -> 70 | ... M20: ='Assumptions'!$B$25+'Assumptions'!$B$26 -> 70 | N20: =SUM(B20:M20) -> 840
A21: TOTAL EXPENSES | B21: =SUM(B15:B20) -> 1928.1 | C21: =SUM(C15:C20) -> 2036.43 | D21: =SUM(D15:D20) -> 2138.44 | E21: =SUM(E15:E20) -> 2227.5 | F21: =SUM(F15:F20) -> 2323.19 | G21: =SUM(G15:G20) -> 2418.88 | H21: =SUM(H15:H20) -> 2500.55 | I21: =SUM(I15:I20) -> 2589.92 | ... M21: =SUM(M15:M20) -> 2896.53 | N21: =SUM(B21:M21) -> 29295.38
A23: NET CASH FLOW (month) | B23: =B12-B21 -> -298.1 | C23: =C12-C21 -> -52.43 | D23: =D12-D21 -> 183.56 | E23: =E12-E21 -> 397.5 | F23: =F12-F21 -> 623.81 | G23: =G12-G21 -> 850.12 | H23: =H12-H21 -> 1039.45 | I23: =I12-I21 -> 1256.08 | ... N23: =N12-N21 -> 10998.62
A24: CUMULATIVE CASH | B24: =B23 -> -298.1 | C24: =B24+C23 -> -350.53 | D24: =C24+D23 -> -166.97 | E24: =D24+E23 -> 230.53 | F24: =E24+F23 -> 854.34 | G24: =F24+G23 -> 1704.46 | H24: =G24+H23 -> 2743.91 | I24: =H24+I23 -> 3999.99 | J24: =I24+J23 -> 5463.02 | ... M24: =L24+M23 -> 10998.62 | N24: =M24 -> 10998.62

Sheet 3-Year Summary
A1: UBHI — 3-YEAR GROWTH & PROFIT (£)
A2: Year 1 links from the monthly tab; Years 2–3 apply the growth multiples on the Assumptions tab.
B3: Year 1 | C3: Year 2 | D3: Year 3 | E3: Y3 vs Y1
A4: REVENUE
A5: Snail Mail Club | B5: ='Year 1 Cash Flow'!N7 -> 9424 | C5: =B5*'Assumptions'!$B$31 -> 23560 | D5: =B5*'Assumptions'!$B$32 -> 32984 | E5: =D5/B5 -> 3.5
A6: Soul Shop | B6: ='Year 1 Cash Flow'!N9 -> 4410 | C6: =B6*'Assumptions'!$B$33 -> 7938 | D6: =B6*'Assumptions'!$B$34 -> 11025 | E6: =D6/B6 -> 2.5
A7: Workshops | B7: ='Year 1 Cash Flow'!N11 -> 26460 | C7: =B7*'Assumptions'!$B$35 -> 34398 | D7: =B7*'Assumptions'!$B$36 -> 42336 | E7: =D7/B7 -> 1.6
A8: TOTAL REVENUE | B8: =SUM(B5:B7) -> 40294 | C8: =SUM(C5:C7) -> 65896 | D8: =SUM(D5:D7) -> 86345 | E8: =D8/B8 -> 2.1428749
A10: EXPENSES
A11: Snail Mail — materials & postage | B11: ='Year 1 Cash Flow'!N15 -> 3534 | C11: =B11*'Assumptions'!$B$31 -> 8835 | D11: =B11*'Assumptions'!$B$32 -> 12369 | E11: =D11/B11 -> 3.5
A12: Soul Shop — materials | B12: ='Year 1 Cash Flow'!N16 -> 1543.5 | C12: =B12*'Assumptions'!$B$33 -> 2778.3 | D12: =B12*'Assumptions'!$B$34 -> 3858.75 | E12: =D12/B12 -> 2.5
A13: Workshops — venue & materials | B13: ='Year 1 Cash Flow'!N17+'Year 1 Cash Flow'!N18 -> 22572 | C13: =B13*'Assumptions'!$B$35 -> 29343.6 | D13: =B13*'Assumptions'!$B$36 -> 36115.2 | E13: =D13/B13 -> 1.6
A14: Payment processing fees | B14: =B8*'Assumptions'!$B$27 -> 805.88 | C14: =C8*'Assumptions'!$B$27 -> 1317.92 | D14: =D8*'Assumptions'!$B$27 -> 1726.9
A15: Overheads (web, marketing) | B15: ='Year 1 Cash Flow'!N20 -> 840 | C15: =B15*'Assumptions'!$B$37 -> 1176 | D15: =C15*'Assumptions'!$B$37 -> 1646.4
A16: TOTAL EXPENSES | B16: =SUM(B11:B15) -> 29295.38 | C16: =SUM(C11:C15) -> 43450.82 | D16: =SUM(D11:D15) -> 55716.25
A18: NET PROFIT (before your pay & tax) | B18: =B8-B16 -> 10998.62 | C18: =C8-C16 -> 22445.18 | D18: =D8-D16 -> 30628.75 | E18: =D18/B18 -> 2.7847812
A19: Net margin % | B19: =B18/B8 -> 0.27295925 | C19: =C18/C8 -> 0.34061521 | D19: =D18/D8 -> 0.35472523
A21: Reminder: NET PROFIT is before Chelsea's own wage and income tax — it's the cash the business throws off.
A22: Biggest lever = workshop venue. A fixed studio instead of per-session hire sharply lifts net profit.
